asm/__init__.py
asm/serializer.py
asm/stack_check.py
asm/ops/__init__.py
asm/ops/abc.py
asm/ops/py30.py
asm/ops/py31.py
asm/ops/py310.py
asm/ops/py311.py
asm/ops/py32.py
asm/ops/py33.py
asm/ops/py34.py
asm/ops/py35.py
asm/ops/py36.py
asm/ops/py37.py
asm/ops/py38.py
asm/ops/py39.py
pyasm-1.1.5.dist-info/LICENSE
pyasm-1.1.5.dist-info/METADATA
pyasm-1.1.5.dist-info/WHEEL
pyasm-1.1.5.dist-info/top_level.txt
pyasm-1.1.5.dist-info/RECORD
