Metadata-Version: 2.1
Name: pyasm
Version: 1.1.5
Summary: A low-level library for manipulating Python Bytecode in an easy way.
Author: Martmists
Author-email: martmists@gmail.com
Classifier: Development Status :: 5 - Production/Stable
Classifier: Programming Language :: Python :: 3
Classifier: Topic :: Software Development :: Libraries :: Application Frameworks
Classifier: Topic :: Software Development :: Code Generators
Classifier: License :: OSI Approved :: MIT License
Requires-Python: >=3.5
License-File: LICENSE
